vcr_unittest/__init__.py
vcr_unittest/testcase.py
vcrpy_unittest-0.1.7.dist-info/DESCRIPTION.rst
vcrpy_unittest-0.1.7.dist-info/METADATA
vcrpy_unittest-0.1.7.dist-info/RECORD
vcrpy_unittest-0.1.7.dist-info/WHEEL
vcrpy_unittest-0.1.7.dist-info/metadata.json
vcrpy_unittest-0.1.7.dist-info/pbr.json
vcrpy_unittest-0.1.7.dist-info/top_level.txt
