Metadata-Version: 1.1
Name: vcrpy-unittest
Version: 0.1.7
Summary: Python unittest integration for vcr.py
Home-page: https://github.com/agriffis/vcrpy-unittest
Author: Aron Griffis
Author-email: aron@scampersand.com
License: MIT
Keywords: vcrpy,vcr.py,unittest,testing,mock,http
Platform: UNKNOWN
Classifier: Development Status :: 5 - Production/Stable
Classifier: Intended Audience :: Developers
Classifier: Topic :: Software Development :: Build Tools
Classifier: License :: OSI Approved :: MIT License
Classifier: Programming Language :: Python
Classifier: Programming Language :: Python :: 2
Classifier: Programming Language :: Python :: 2.7
Classifier: Programming Language :: Python :: 3
Classifier: Programming Language :: Python :: 3.4
Classifier: Programming Language :: Python :: 3.5
Classifier: Programming Language :: Python :: 3.6
Classifier: Programming Language :: Python :: 3.7
